sort/__init__.py
sort/bubble_sort.py
sort/insertion_sort.py
sort/quick_sort.py
peter_sort-0.1.7.dist-info/LICENSE
peter_sort-0.1.7.dist-info/METADATA
peter_sort-0.1.7.dist-info/WHEEL
peter_sort-0.1.7.dist-info/top_level.txt
peter_sort-0.1.7.dist-info/RECORD
